svgen/__init__.py
svgen/__main__.py
svgen/app.py
svgen/config.py
svgen/dev_requirements.txt
svgen/display.py
svgen/entry.py
svgen/inkscape.py
svgen/py.typed
svgen/requirements.txt
svgen/script.py
svgen/attribute/__init__.py
svgen/attribute/style.py
svgen/attribute/viewbox.py
svgen/cartesian/__init__.py
svgen/cartesian/angle.py
svgen/cartesian/circle.py
svgen/cartesian/mutate.py
svgen/cartesian/plane.py
svgen/cartesian/point.py
svgen/cartesian/rectangle/__init__.py
svgen/cartesian/rectangle/corner.py
svgen/cartesian/rectangle/grid.py
svgen/color/__init__.py
svgen/color/alpha.py
svgen/color/conversion.py
svgen/color/hsl.py
svgen/color/numbers.py
svgen/color/resolve.py
svgen/color/rgb.py
svgen/color/theme/__init__.py
svgen/color/theme/manager.py
svgen/color/theme/visualize.py
svgen/data/themes/blue_gray.yaml
svgen/data/themes/blue_gray_analogous1.yaml
svgen/data/themes/blue_gray_analogous2.yaml
svgen/data/themes/blue_gray_complementary.yaml
svgen/data/themes/blue_gray_primary.yaml
svgen/data/themes/blue_gray_triadic1.yaml
svgen/data/themes/blue_gray_triadic2.yaml
svgen/data/themes/bootstrap.yaml
svgen/data/themes/gray.yaml
svgen/data/themes/guild.yaml
svgen/element/__init__.py
svgen/element/circle.py
svgen/element/line.py
svgen/element/path.py
svgen/element/rect.py
svgen/element/svg.py
svgen/element/text.py
svgen/element/html/__init__.py
svgen/element/mixins/__init__.py
svgen/generation/__init__.py
svgen/generation/images.py
svgen/shapes/__init__.py
svgen/shapes/chip.py
svgen/shapes/pins.py
svgen-0.9.3.dist-info/licenses/LICENSE
svgen-0.9.3.dist-info/METADATA
svgen-0.9.3.dist-info/WHEEL
svgen-0.9.3.dist-info/entry_points.txt
svgen-0.9.3.dist-info/top_level.txt
svgen-0.9.3.dist-info/RECORD
